doxtrings/__init__.py
doxtrings/documentable.py
doxtrings/cli/__init__.py
doxtrings/cli/scan.py
doxtrings/config/__init__.py
doxtrings/config/builder.py
doxtrings/config/merge.py
doxtrings/config/models.py
doxtrings/core/__init__.py
doxtrings/core/report.py
doxtrings/core/search.py
doxtrings/core/parser/__init__.py
doxtrings/core/parser/file_parser.py
doxtrings/core/parser/node_parser.py
doxtrings-0.2.1.dist-info/entry_points.txt
doxtrings-0.2.1.dist-info/WHEEL
doxtrings-0.2.1.dist-info/METADATA
doxtrings-0.2.1.dist-info/RECORD
