Metadata-Version: 2.1
Name: doxtrings
Version: 0.2.1
Summary: a package that can ensure your docstrings are correct
Author-email: Lucas Pereira <pereira.lucas@bcg.com>
Requires-Python: ~=3.8
Requires-Dist: tomli==2.*
Requires-Dist: docstring-parser==0.15
Requires-Dist: bump2version==1.0.1 ; extra == "ci"
Requires-Dist: pre-commit==3.2.2 ; extra == "dev"
Requires-Dist: black==23.3.0 ; extra == "dev"
Requires-Dist: pyright==1.1.309 ; extra == "dev"
Requires-Dist: isort ; extra == "dev"
Requires-Dist: mkdocstrings[python]==0.22.0 ; extra == "docs"
Requires-Dist: mkdocs-gen-files==0.5.0 ; extra == "docs"
Requires-Dist: mkdocs-literate-nav==0.5.0 ; extra == "docs"
Requires-Dist: mkdocs-section-index==0.3.5 ; extra == "docs"
Requires-Dist: mkdocs-material==9.2.5 ; extra == "docs"
Requires-Dist: pytest==7.3.1 ; extra == "test"
Requires-Dist: pytest-cov==4.0.0 ; extra == "test"
Provides-Extra: ci
Provides-Extra: dev
Provides-Extra: docs
Provides-Extra: test
